modpybass/__init__.py
modpybass/bass.py
modpybass/pybass.py
modpybass/pybass_aac.py
modpybass/pybass_ac3.py
modpybass/pybass_adx.py
modpybass/pybass_aix.py
modpybass/pybass_alac.py
modpybass/pybass_ape.py
modpybass/pybass_mpc.py
modpybass/pybass_ofr.py
modpybass/pybass_sfx.py
modpybass/pybass_spx.py
modpybass/pybass_tta.py
modpybass/pybass_vst.py
modpybass/pybassasio.py
modpybass/pybassflac.py
modpybass/pybassmidi.py
modpybass/pybassmix.py
modpybass/pybasswasapi.py
modpybass/pybasswma.py
modpybass/pyogginfo.py
modpybass/pytags.py
modpybass/wx_bass_control.py
modpybass/wx_ctrl_phoenix.py
modpybass/lib/aarch64/libbass.dylib
modpybass/lib/aarch64/libbass.so
modpybass/lib/aarch64/libbass_fx.so
modpybass/lib/aarch64/libbass_vst.dylib
modpybass/lib/aarch64/libbassmidi.so
modpybass/lib/aarch64/libbassmix.dylib
modpybass/lib/aarch64/libbassmix.so
modpybass/lib/aarch64/libtags.dylib
modpybass/lib/aarch64/libtags.so
modpybass/lib/armhf/libbass.dylib
modpybass/lib/armhf/libbass.so
modpybass/lib/armhf/libbass_fx.so
modpybass/lib/armhf/libbass_vst.dylib
modpybass/lib/armhf/libbassmidi.so
modpybass/lib/armhf/libbassmix.dylib
modpybass/lib/armhf/libbassmix.so
modpybass/lib/armhf/libtags.dylib
modpybass/lib/armhf/libtags.so
modpybass/lib/x64/bass.dll
modpybass/lib/x64/bass_fx.dll
modpybass/lib/x64/bass_vst.dll
modpybass/lib/x64/bassmidi.dll
modpybass/lib/x64/bassmix.dll
modpybass/lib/x64/basswasapi.dll
modpybass/lib/x64/libbass.dylib
modpybass/lib/x64/libbass.so
modpybass/lib/x64/libbass_fx.so
modpybass/lib/x64/libbass_vst.dylib
modpybass/lib/x64/libbassmidi.so
modpybass/lib/x64/libbassmix.dylib
modpybass/lib/x64/libbassmix.so
modpybass/lib/x64/libtags.dylib
modpybass/lib/x64/libtags.so
modpybass/lib/x64/tags.dll
modpybass/lib/x86/bass.dll
modpybass/lib/x86/bass_fx.dll
modpybass/lib/x86/bass_vst.dll
modpybass/lib/x86/bassmidi.dll
modpybass/lib/x86/bassmix.dll
modpybass/lib/x86/basswasapi.dll
modpybass/lib/x86/libbass.dylib
modpybass/lib/x86/libbass.so
modpybass2-0.5.8.dist-info/licenses/LICENSE
modpybass2-0.5.8.dist-info/METADATA
modpybass2-0.5.8.dist-info/WHEEL
modpybass2-0.5.8.dist-info/top_level.txt
modpybass2-0.5.8.dist-info/RECORD
