Metadata-Version: 2.4
Name: modpybass2
Version: 0.5.8
Summary: Modified pybass
Home-page: https://github.com/johannmkammiste/modpybassmacos
Author: Taehong Kim
Author-email: Johann Mattias kammiste <johannmkammiste@gmail.com>, Maxim Kolosov <pyirrlicht@gmail.com>
License-Expression: MIT
Project-URL: Homepage, https://github.com/johannmkammiste/modpybassmacos
Project-URL: Issues, https://github.com/johannkammiste/modpybassmacos/issues
Keywords: pybass,modpybass,BASS,music,audio,audio library
Classifier: Programming Language :: Python :: 3
Classifier: Operating System :: OS Independent
Requires-Python: >=3.9
License-File: LICENSE
Dynamic: author
Dynamic: home-page
Dynamic: license-file
